{"m_Faction":"None","m_SocketCount":1,"m_AttributeFlags":"\"Unknown\"","m_ResourceCost":5,"m_Threshold":[{"m_ColorFlags":"Sapphire","m_ThresholdColorRequirement":1}],"m_BaseAttackValue":"1","m_BaseHealthValue":"5","m_FlavorText":"\u003ci\u003eThe wendigo is a cannibalistic, evil spirit that is able to occupy the body of a sentient creature.\u003c/i\u003e","m_ResourceSymbolImagePath":"","m_Unique":0,"m_EquipmentSlots":[{"m_Guid":"ae1478ff-1440-412c-a823-cb06aae57647"},{"m_Guid":"bae7e577-1c72-4f07-8f7b-0e023f5b33bf"},{"m_Guid":"00000000-0000-0000-0000-000000000000"}],"m_Id":{"m_Guid":"6e63690a-b58b-43c9-bb23-a0f2c188f616"},"m_SetId":{"m_Guid":"0382f729-7710-432b-b761-13677982dcd2"},"m_Name":"Mistborn Wendigo","m_CardNumber":258,"m_ColorFlags":"\"Sapphire\"","m_CardImagePath":"hex00278","m_CardType":"\"Troop\"","m_CardSubtype":"Spirit","m_CardRarity":"Uncommon","m_ArtistName":"Mark Tarrisse","m_GameText":"\u003cb\u003eSOCKETABLE MINOR\u003c/b\u003e\u003cp\u003e\u003cp\u003e[(1)] [ARROWR]  Switch this troop\u0027s [ATK] and [DEF] this turn.","m_DesignNotes":"","m_Unlimited":0,"m_Tradeable":1,"m_HasExtendedLayout":1,"m_DefaultLayout":{"m_Id":{"m_Guid":"9bfc50c0-1861-4c6a-83bb-d14062bc9306"},"m_Name":"","m_PortraitRotation":0.0,"m_PortraitLeft":0.06640625,"m_PortraitBottom":0.73769325,"m_PortraitRight":0.9091797,"m_PortraitTop":0.0185546875},"m_ExtendedLayout":{"m_Id":{"m_Guid":"00000000-0000-0000-0000-000000000000"},"m_Name":"","m_PortraitRotation":0.0,"m_PortraitLeft":0.09277344,"m_PortraitBottom":0.997078538,"m_PortraitRight":0.90625,"m_PortraitTop":9.765625E-4}}