{"m_Faction":"None","m_SocketCount":0,"m_AttributeFlags":"\"Unknown\"","m_ResourceCost":2,"m_Threshold":[{"m_ColorFlags":"Blood","m_ThresholdColorRequirement":2}],"m_BaseAttackValue":"0","m_BaseHealthValue":"0","m_FlavorText":"\u003ci\u003eVennen warlocks organize public rituals where \"heretics\" are tortured and executed.\u003c/i\u003e","m_ResourceSymbolImagePath":"","m_Unique":0,"m_EquipmentSlots":[{"m_Guid":"bafb6c91-444e-4760-8f46-41d2c505727d"},{"m_Guid":"c4beec12-b0d7-4d39-b888-ad72599918f2"},{"m_Guid":"00000000-0000-0000-0000-000000000000"}],"m_Id":{"m_Guid":"53abef3a-5d96-4374-93fb-56f44eb1361d"},"m_SetId":{"m_Guid":"0382f729-7710-432b-b761-13677982dcd2"},"m_Name":"Inquisition","m_CardNumber":72,"m_ColorFlags":"\"Blood\"","m_CardImagePath":"hex00092","m_CardType":"\"BasicAction\"","m_CardSubtype":"","m_CardRarity":"Common","m_ArtistName":"","m_GameText":"Target opposing champion reveals their hand.  Choose a non-resource card from it. They discard that card.","m_DesignNotes":"sam wants distress  Choose troop or non-troop. Target opposing champion reveals all non-resource cards of the chosen type in their hand and you choose one of them. That champion discards that card.","m_Unlimited":0,"m_Tradeable":1,"m_HasExtendedLayout":1,"m_DefaultLayout":{"m_Id":{"m_Guid":"8dff3e79-17d9-4d8a-9262-2589c609e841"},"m_Name":"","m_PortraitRotation":0.0,"m_PortraitLeft":0.09765625,"m_PortraitBottom":0.6953125,"m_PortraitRight":0.866729259,"m_PortraitTop":0.0390625},"m_ExtendedLayout":{"m_Id":{"m_Guid":"00000000-0000-0000-0000-000000000000"},"m_Name":"","m_PortraitRotation":0.0,"m_PortraitLeft":0.09277344,"m_PortraitBottom":0.999023438,"m_PortraitRight":0.906243265,"m_PortraitTop":0.0029296875}}